CHANGELOG.md
README.md
mitol/__init__.py
mitol/apigateway/__init__.py
mitol/apigateway/api.py
mitol/apigateway/apps.py
mitol/apigateway/backends.py
mitol/apigateway/middleware.py
mitol/apigateway/middleware_channels.py
mitol/apigateway/py.typed
mitol/apigateway/urls.py
mitol/apigateway/views.py
mitol/apigateway/management/__init__.py
mitol/apigateway/management/commands/__init__.py
mitol/apigateway/management/commands/promote_user.py
mitol/apigateway/settings/__init__.py
mitol_django_apigateway-2025.8.14.dist-info/METADATA
mitol_django_apigateway-2025.8.14.dist-info/WHEEL
mitol_django_apigateway-2025.8.14.dist-info/RECORD
