Metadata-Version: 2.4
Name: mitol-django-apigateway
Version: 2025.8.14
Summary: MIT Open Learning Django app for API Gateway support
License-Expression: BSD-3-Clause
Requires-Python: >=3.10
Requires-Dist: channels>=4.2.0
Requires-Dist: django-stubs>=1.13.1
Requires-Dist: django>=3.0
Requires-Dist: edx-opaque-keys==2.2.2
